entanglement_prediction/__init__.py
entanglement_prediction/quantum_circuit.py
error_correction/__init__.py
error_correction/hamming_code.py
error_correction/repetition_code.py
phase_estimation/__init__.py
phase_estimation/optimized_phase_estimation.py
phase_estimation/quantum_phase_estimation.py
quantumvista-1.0.0.dist-info/METADATA
quantumvista-1.0.0.dist-info/WHEEL
quantumvista-1.0.0.dist-info/top_level.txt
quantumvista-1.0.0.dist-info/RECORD
