Metadata-Version: 2.1
Name: quantumvista
Version: 1.0.0
Summary: A Python package for quantum computing concepts and algorithms.
Home-page: https://github.com/yourusername/nebula
Author: Hemorra
Author-email: blestduck24@proton.me
Classifier: Programming Language :: Python :: 3
Classifier: License :: OSI Approved :: MIT License
Classifier: Operating System :: OS Independent
Requires-Python: >=3.6
